py_dep_graph/__about__.py
py_dep_graph/__init__.py
py_dep_graph-0.0.1.dist-info/METADATA
py_dep_graph-0.0.1.dist-info/WHEEL
py_dep_graph-0.0.1.dist-info/licenses/LICENSE
py_dep_graph-0.0.1.dist-info/RECORD
